main.py
setup.py
Bytedps.egg-info/PKG-INFO
Bytedps.egg-info/SOURCES.txt
Bytedps.egg-info/dependency_links.txt
Bytedps.egg-info/requires.txt
Bytedps.egg-info/top_level.txt